<?xml version="1.0"?>
<!-- Generated by lang::catalog::export_messages_to_file on 2003 January 21 17:29 -->
<message_catalog package_key="calendar" package_version="1.0" locale="pl_PL" charset="ISO-8859-2">

  <msg key="_You_may_choose_to">, Mo¿esz wybraæ:</msg>
  <msg key="Add">Dodaj</msg>
  <msg key="add">dodaj</msg>
  <msg key="Add_a_new_Audience">Dodaj now± Publiczno¶æ</msg>
  <msg key="add_an_event">dodaj termin</msg>
  <msg key="Add_Item">Dodatj Termin</msg>
  <msg key="Add_Recurrence">Dodaj Powtórzenia</msg>
  <msg key="All_Day_Event">Wydarzenie Ca³odzienne</msg>
  <msg key="all_events">wszystkie wydarzenia</msg>
  <msg key="and_Time">i Czas</msg>
  <msg key="Attachments">Za³±czniki:</msg>
  <msg key="Audiences_for_item">Publiczno¶æ dla wydarzenia</msg>
  <msg key="Calendar">Kalendarz</msg>
  <msg key="Calendar_Add_Item">Kalendarz: Dodaj Termin</msg>
  <msg key="Calendar_Edit_Item">Kalendarz: Edytuj Termin</msg>
  <msg key="Calendar_Item">Termin</msg>
  <msg key="Calendar_Item_Delete">Usuñ Termin</msg>
  <msg key="Calendar_Item_Types">Typ Terminu</msg>
  <msg key="Calendar_Name">Nazwa Kalendarza</msg>
  <msg key="Calendar_Permissions">&quot;Dostêp do Kalendarza&quot;</msg>
  <msg key="Calendar_Permissions_1">Dostêp do Kalendarza</msg>
  <msg key="Calendar_Preferences">&quot;Ustawienia Kalendarza&quot;</msg>
  <msg key="Calendars">Kalendarze</msg>
  <msg key="Choose">Wybierz</msg>
  <msg key="Current_Permissions">Aktualne Prawa</msg>
  <msg key="Date">Data:</msg>
  <msg key="Date_1">Data</msg>
  <msg key="day">dzieñ</msg>
  <msg key="day_s">dzieñ (dni)</msg>
  <msg key="Delete">Usuñ</msg>
  <msg key="delete">usuñ</msg>
  <msg key="Description">Opis</msg>
  <msg key="Details">Szczegó³y:</msg>
  <msg key="DEVELOPER_NOTE">Nota Programisty:</msg>
  <msg key="Edit">Edytuj</msg>
  <msg key="edit">edytuj</msg>
  <msg key="Edit_All_Occurrences">Edytowaæ wszystkie wyst±pienia?</msg>
  <msg key="Edit_Item">Edytuj Termin</msg>
  <msg key="End_Time">Koniec</msg>
  <msg key="For">Dla</msg>
  <msg key="Friday">Pi±tek</msg>
  <msg key="from">z</msg>
  <msg key="Grant">Przyznaj</msg>
  <msg key="Grant_Permissions">Przyznaj Prawa</msg>
  <msg key="Item">Termin</msg>
  <msg key="Item_Type">Typ Terminu</msg>
  <msg key="lt_apply_group_user_spec">je¶li trzeba przyznaj prawa specyficzne dla grupy, u¿ytkownika</msg>
  <msg key="lt_Are_you_sure_you_want">Czy na pewno usun±æ ten kalendarz? Wszystkie terminy i prawa z nimi zwi±zane zostan± usuniête wraz z nim.</msg>
  <msg key="lt_Are_you_sure_you_want_1">Czy na pewno usun±æ ten termin?</msg>
  <msg key="lt_Audiences_for_calenda">Publiczno¶æ kalendarza</msg>
  <msg key="lt_Calendar_Administrati">Administracja Kalendarzem</msg>
  <msg key="lt_Calendar_Administrati_1">Administracja Kalendarzem dla U¿ytkownika</msg>
  <msg key="lt_Calendar_Choose_Calen">Kalendarz: Wybierz Kalendarz</msg>
  <msg key="lt_Calendar_detail_listi">Szczegó³y kalendarza: pe³na informacja o kalendarzu</msg>
  <msg key="lt_Calendar_Item_Adminis">Administracja Terminem /???/</msg>
  <msg key="lt_Calendar_Item_Permiss">&quot;Prawa dostêpu do Terminu&quot;</msg>
  <msg key="lt_Calendars_Repeating_E">Kalendarze: Wydarzenia Powtarzaj±ce siê</msg>
  <msg key="lt_Create_a_new_calendar">Utwórz nowy kalendarz</msg>
  <msg key="lt_create_the_calendar_o">utwórz obiekt kalendarza, zmieñ prawa dostêpu, je¶li trzeba</msg>
  <msg key="lt_delete_all_occurrence">usuñ wszystkie wyst±pienia</msg>
  <msg key="lt_delete_only_this_inst">usuñ tylko to wyst±pienie</msg>
  <msg key="lt_Edit_ALL_instances_of">Edytuj WSZYSTKIE terminy tego wydarzenia</msg>
  <msg key="lt_Edit_only_THIS_instan">Edytuj tylko TEN termin</msg>
  <msg key="lt_Edit_your_Calendar_Pr">Edytuj Ustawienia twojego Kalendarza</msg>
  <msg key="lt_everyone_have_read_pe">wszyscy, nawet niezarejestrowani, mog± ogl±daæ terminy.</msg>
  <msg key="lt_Hide_Checked_Calendar">Ukryj Zaznaczone Kalendarze</msg>
  <msg key="lt_Manage_Calendar_Audie">Zarz±dzaj Publiczno¶ci± Kalendarza</msg>
  <msg key="lt_Manage_the_audience_t">Zarz±dzaj Publiczno¶ci± tego terminu</msg>
  <msg key="lt_no_parties_exist_cont">nie istniej± ¿adne jednostki. Skontaktuj siê z Adminem Systemu.</msg>
  <msg key="lt_no_privilege_exist_co">nie istniej± prawa dostêpu. Skontaktuj siê z Adminem Systemu.</msg>
  <msg key="lt_no_privilege_has_been">nie przyznano ¿adnych przywilejów</msg>
  <msg key="lt_only_those_you_choose">tylko ci u¿ytkownicy, których okre¶lisz jako publiczno¶æ tego kalendarza bêd¿ mogli przegl±daæ terminy.</msg>
  <msg key="lt_Repeat_this_event_unt">Powtarzaj to wydarzenia do:</msg>
  <msg key="lt_select_groups_andor_u">wybierz grupy i/lub u¿ytkowników, którzy stanowiæ bêd± publiczno¶æ tego kalendarza</msg>
  <msg key="lt_the_calendar_creation">Tworzenie kalendarza sk³ada siê z nastêpuj±cych kroków:</msg>
  <msg key="lt_The_following_is_a__l">To s± kalendarze, do których masz dostêp. Niniejsza lista pojawi siê w Twoim kalendarzu jako mo¿liwo¶æ wyboru wydarzeñ spo¶ród wielu kalendarzy. Mo¿esz umie¶ciæ wybrane kalendarze na swojej li¶cie.</msg>
  <msg key="lt_There_are_no_audience">Brak publiczno¶ci dla tego kalendarza</msg>
  <msg key="lt_This_event_is_a_singl">To jest pojedynczy, niepowtarzalny termin</msg>
  <msg key="lt_This_is_a_repeating_e">To jest termin powtarzalny</msg>
  <msg key="lt_You_are_choosing_to_m">Ustawiasz powtarzanie tego terminu, dlatego pojawi siê wiele razy w Twoim kalendarzu. Oto szczegó³y terminu:</msg>
  <msg key="lt_You_can_manage_the_fo">Mo¿esz zarz±dzaæ nastêpuj±cymi kalendarzami</msg>
  <msg key="lt_You_have_no_party_wid">Nie masz ogólnych kalendarzy</msg>
  <msg key="lt_Your_are_in_the_follo">Jeste¶ cz³onkiem grupy:</msg>
  <msg key="Monday">Poniedzia³ek</msg>
  <msg key="New_Type">Nowy Typ:</msg>
  <msg key="No">Nie</msg>
  <msg key="No_Calendars">Brak Kalendarzy</msg>
  <msg key="no_keep_it">nie, zachowaj to</msg>
  <msg key="No_Time">Brak Czasu</msg>
  <msg key="Note">Uwaga</msg>
  <msg key="of_the_month">miesi±ca</msg>
  <msg key="of_the_week">tygodnia</msg>
  <msg key="Private">Prywatne:</msg>
  <msg key="private">prywatne</msg>
  <msg key="Private_1">Prywatne</msg>
  <msg key="Public">Publiczne:</msg>
  <msg key="public">publiczne</msg>
  <msg key="Repeat">Powtarzaj</msg>
  <msg key="Repeat_1">Powtarzaæ?</msg>
  <msg key="Repeat_every">Powtarzaj ka¿dego</msg>
  <msg key="repeated">powtarzane</msg>
  <msg key="revoke">odwo³aj</msg>
  <msg key="same">taki sam</msg>
  <msg key="Saturday">Sobota</msg>
  <msg key="Select_Calendars">Wybierz Kalendarze</msg>
  <msg key="single_event">pojedynczy termin</msg>
  <msg key="Start_Time">Pocz±tek</msg>
  <msg key="Submit_query">Wy¶lij Zapytanie</msg>
  <msg key="Sunday">Niedziela</msg>
  <msg key="sync_with_Outlook">synchronizuj z Outlookiem:</msg>
  <msg key="This_event_is">Ten termin jest</msg>
  <msg key="Thursday">Czwartek</msg>
  <msg key="Time">Czas:</msg>
  <msg key="Title">Tytu³:</msg>
  <msg key="Title_1">Tytu³</msg>
  <msg key="to">do</msg>
  <msg key="Tuesday">Wtorek</msg>
  <msg key="Type">Typ:</msg>
  <msg key="Type_1">Typ</msg>
  <msg key="Use_Hours_Below">U¿yj godzin poni¿ej:</msg>
  <msg key="Wednesday">¦roda</msg>
  <msg key="year">rok</msg>
  <msg key="Yes">Tak</msg>
  <msg key="yes_delete_it">tak, uswaj</msg>
  <msg key="Yes_I_am_sure">Tak, na pewno!</msg>
</message_catalog>
